pygame_ui_toolkit/__init__.py
pygame_ui_toolkit/utils.py
pygame_ui_toolkit/elements/__init__.py
pygame_ui_toolkit/elements/button.py
pygame_ui_toolkit/elements/dropdown.py
pygame_ui_toolkit/elements/input.py
pygame_ui_toolkit/elements/slider.py
pygame_ui_toolkit/elements/text.py
pygame_ui_toolkit/elements/toggle.py
pygame_ui_toolkit/presets/__init__.py
pygame_ui_toolkit/presets/button_colour_change.py
pygame_ui_toolkit/presets/button_size_change.py
pygame_ui_toolkit/presets/input_size_colour_change.py
pygame_ui_toolkit/presets/slider_value_text.py
pygame_ui_toolkit-1.0.5.dist-info/LICENSE
pygame_ui_toolkit-1.0.5.dist-info/METADATA
pygame_ui_toolkit-1.0.5.dist-info/WHEEL
pygame_ui_toolkit-1.0.5.dist-info/top_level.txt
pygame_ui_toolkit-1.0.5.dist-info/RECORD
