Metadata-Version: 2.1
Name: pygame-ui-toolkit
Version: 1.0.5
Summary: A package for creating UI elements in pygame
Home-page: https://github.com/Ben-Edwards44/pygame-ui-toolkit
Author: Ben Edwards
License: MIT
Classifier: Programming Language :: Python :: 3
Classifier: License :: OSI Approved :: MIT License
Classifier: Operating System :: OS Independent
Classifier: Topic :: Games/Entertainment
Classifier: Intended Audience :: Developers
Requires-Python: >=3.6
License-File: LICENSE
Requires-Dist: pygame >=2.0.0
